hayahalil/__init__.py
hayahalil-0.0.2.dist-info/LICENSE
hayahalil-0.0.2.dist-info/METADATA
hayahalil-0.0.2.dist-info/WHEEL
hayahalil-0.0.2.dist-info/top_level.txt
hayahalil-0.0.2.dist-info/RECORD
