Metadata-Version: 2.1
Name: hayahalil
Version: 0.0.2
Summary: Hayahalil project
Home-page: https://github.com/pksung1/hayahalil
Author: pksung1
Author-email: pksung1@gmail.com
License: UNKNOWN
Platform: UNKNOWN
Classifier: Programming Language :: Python :: 3
Classifier: License :: OSI Approved :: MIT License
Classifier: Operating System :: OS Independent
Requires-Python: >=3.5
